interaction_inference/__init__.py
interaction_inference/bootstrap.py
interaction_inference/correlation.py
interaction_inference/dataset.py
interaction_inference/hypothesis.py
interaction_inference/minimization.py
interaction_inference/results.py
interaction_inference/simulation.py
interaction_inference/truncation.py
interaction_inference-0.0.1.dist-info/METADATA
interaction_inference-0.0.1.dist-info/WHEEL
interaction_inference-0.0.1.dist-info/licenses/LICENSE
interaction_inference-0.0.1.dist-info/RECORD
