Metadata-Version: 2.4
Name: interaction-inference
Version: 0.0.1
Summary: Infer gene interaction via constrained optimization
Project-URL: Repository, https://github.com/willjgh/interaction-inference
Author-email: William Hilton <williamjgh2000@gmail.com>
License-File: LICENSE
Keywords: inference,optimization,scRNA-seq
Classifier: License :: OSI Approved :: MIT License
Classifier: Operating System :: OS Independent
Classifier: Programming Language :: Python :: 3
Requires-Python: >=3.8
Requires-Dist: gurobipy==11.0
Requires-Dist: jinja2
Requires-Dist: matplotlib
Requires-Dist: numpy<2
Requires-Dist: pandas
Requires-Dist: scipy
Requires-Dist: seaborn
Requires-Dist: tqdm
